classic/signals/__init__.py
classic/signals/decorator.py
classic/signals/hub.py
classic/signals/reaction.py
classic/signals/signal.py
classic/signals/utils.py
classic_signals-0.1.1.dist-info/licenses/LICENSE
classic_signals-0.1.1.dist-info/METADATA
classic_signals-0.1.1.dist-info/WHEEL
classic_signals-0.1.1.dist-info/top_level.txt
classic_signals-0.1.1.dist-info/RECORD
